nh_prototype/__init__.py
nh_prototype/utils.py
nh_prototype-0.0.1.dist-info/WHEEL
nh_prototype-0.0.1.dist-info/METADATA
nh_prototype-0.0.1.dist-info/RECORD
