Metadata-Version: 2.1
Name: nh-prototype
Version: 0.0.1
Summary: 
License: MIT
Author: Your Name
Author-email: you@example.com
Requires-Python: >=3.8,<4.0
Classifier: License :: OSI Approved :: MIT License
Classifier: Programming Language :: Python :: 3
Classifier: Programming Language :: Python :: 3.8
Classifier: Programming Language :: Python :: 3.9
Requires-Dist: joblib (>=1.0.1,<2.0.0)
Requires-Dist: mlflow (>=1.15.0,<2.0.0)
Requires-Dist: pyspark (>=3.1.1,<4.0.0)
